ndclib/__init__.py
ndclib/exceptions.py
ndclib/format.py
ndclib/ndc.py
ndclib/provider.py
ndclib-1.0rc1.dist-info/LICENSE
ndclib-1.0rc1.dist-info/METADATA
ndclib-1.0rc1.dist-info/WHEEL
ndclib-1.0rc1.dist-info/top_level.txt
ndclib-1.0rc1.dist-info/RECORD
