Metadata-Version: 2.2
Name: ndclib
Version: 1.0rc1
Summary: A Python library for manipulating National Drug Codes (NDCs)
Author-email: Eddie Cosma <eddie.cosma@gmail.com>
License: MIT License
Project-URL: Repository, https://github.com/eddie-cosma/ndclib
Project-URL: Issues, https://github.com/eddie-cosma/ndclib/issues
Classifier: Programming Language :: Python :: 3
Classifier: Programming Language :: Python :: 3.10
Classifier: Programming Language :: Python :: 3.11
Classifier: Programming Language :: Python :: 3.12
Classifier: Operating System :: OS Independent
Classifier: Intended Audience :: Healthcare Industry
Classifier: License :: OSI Approved :: MIT License
Classifier: Topic :: Software Development :: Libraries
Requires-Python: >=3.10
License-File: LICENSE
Requires-Dist: requests~=2.32.3
Provides-Extra: dev
Requires-Dist: pytest~=8.3.4; extra == "dev"
Requires-Dist: black~=24.10.0; extra == "dev"
Requires-Dist: twine~=6.0.1; extra == "dev"
Requires-Dist: build~=1.2.2.post1; extra == "dev"
